renamed/__init__.py
renamed/client.py
renamed/exceptions.py
renamed/py.typed
renamed/types.py
renamed-0.1.0b4.dist-info/METADATA
renamed-0.1.0b4.dist-info/WHEEL
renamed-0.1.0b4.dist-info/RECORD
