Metadata-Version: 2.4
Name: renamed
Version: 0.1.0b4
Summary: Official Python SDK for renamed.to API
Project-URL: Homepage, https://www.renamed.to
Project-URL: Documentation, https://www.renamed.to/docs/api-docs
Project-URL: Repository, https://github.com/renamed-to/renamed-sdk
Project-URL: Issues, https://github.com/renamed-to/renamed-sdk/issues
Project-URL: Changelog, https://github.com/renamed-to/renamed-sdk/releases
Author: renamed.to
License-Expression: MIT
Keywords: ai,document,ocr,pdf,rename,renamed,sdk
Classifier: Development Status :: 4 - Beta
Classifier: Intended Audience :: Developers
Classifier: License :: OSI Approved :: MIT License
Classifier: Operating System :: OS Independent
Classifier: Programming Language :: Python :: 3
Classifier: Programming Language :: Python :: 3.9
Classifier: Programming Language :: Python :: 3.10
Classifier: Programming Language :: Python :: 3.11
Classifier: Programming Language :: Python :: 3.12
Classifier: Programming Language :: Python :: 3.13
Classifier: Topic :: Software Development :: Libraries :: Python Modules
Classifier: Typing :: Typed
Requires-Python: >=3.9
Requires-Dist: httpx>=0.25.0
Requires-Dist: pydantic>=2.0.0
Provides-Extra: dev
Requires-Dist: pytest-asyncio>=0.21.0; extra == 'dev'
Requires-Dist: pytest-cov>=4.0.0; extra == 'dev'
Requires-Dist: pytest>=7.0.0; extra == 'dev'
Requires-Dist: respx>=0.20.0; extra == 'dev'
